{"scene":{
   "texte":"je *.",
   "possibilite":{
      "choix":[
         "ramassai",
         "ramasse",
         "ramasserai"
      ],
      "valeur":[
         "1",
         "0",
         "0"
      ],
      "feedback":[
         "feedback passé",
         "feedback présent",
         "feedback futur"
      ],
      "increments":[
         [
            { "key":"l" , "value":"1" }
         ],
         [
            { "key":"l" , "value":"1" }
         ],
         [
            { "key":"l" , "value":"1" }
         ]
      ],
      "suites":[
         {
            "sceneSuivante":"C3AQ1",
            "choix":"2",
            "scene":[
               "C2AQ1",
               "C2AQ2",
               "C2AQ3"
            ]
         },
         {
            "sceneSuivante":"C3BQ1",
            "choix":"non",
            "scene":[
               "C2AQ1",
               "C2AQ2",
               "C2AQ3"
            ]
         }
      ]
   }
}}